LICENSE
MANIFEST.in
README.md
setup.cfg
setup.py
django_job_board.egg-info/PKG-INFO
django_job_board.egg-info/SOURCES.txt
django_job_board.egg-info/dependency_links.txt
django_job_board.egg-info/requires.txt
django_job_board.egg-info/top_level.txt
job_board/__init__.py
job_board/apps.py
job_board/decorators.py
job_board/models.py
job_board/tasks.py
job_board/tests.py
job_board/urls.py
job_board/views.py
job_board/admin/__init__.py
job_board/admin/assessment_admin.py
job_board/admin/candidate_admin.py
job_board/admin/job_admin.py
job_board/apis/__init__.py
job_board/apis/assessment.py
job_board/apis/authentication.py
job_board/apis/job.py
job_board/auth/CandidateAuth.py
job_board/auth/__init__.py
job_board/migrations/0001_initial.py
job_board/migrations/0002_job_assessment.py
job_board/migrations/0003_alter_job_assessment.py
job_board/migrations/0004_auto_20210629_1947.py
job_board/migrations/0005_auto_20210702_1224.py
job_board/migrations/0006_auto_20210714_1333.py
job_board/migrations/0007_auto_20210714_1637.py
job_board/migrations/0008_resetpassword.py
job_board/migrations/0009_jobadditionalfield.py
job_board/migrations/0010_auto_20210720_1942.py
job_board/migrations/0011_alter_candidatejob_step.py
job_board/migrations/0012_alter_candidatejob_step.py
job_board/migrations/0013_candidateassessmentanswer.py
job_board/migrations/0014_candidateassessmentanswer_candidate_job.py
job_board/migrations/0015_candidateassessment.py
job_board/migrations/0016_auto_20210724_2250.py
job_board/migrations/0017_auto_20210724_2306.py
job_board/migrations/0018_auto_20210724_2332.py
job_board/migrations/0019_auto_20210725_1648.py
job_board/migrations/0020_remove_candidateassessment_exam_type.py
job_board/migrations/0021_alter_candidateassessment_assessment.py
job_board/migrations/0022_auto_20210725_1700.py
job_board/migrations/0023_assessment_pass_score.py
job_board/migrations/0024_alter_assessment_description.py
job_board/migrations/0025_assessment_open_to_start.py
job_board/migrations/0026_auto_20210727_2234.py
job_board/migrations/0027_auto_20210728_1546.py
job_board/migrations/0028_remove_assessment_score.py
